filedups/__init__.py
filedups/argparser_custom.py
filedups/classes.py
filedups/common_types.py
filedups/constants.py
filedups/csv_io.py
filedups/filedups_api.py
filedups/grouper_funs.py
filedups/main.py
filedups/util.py
filedups-1.0.0.dist-info/LICENSE.txt
filedups-1.0.0.dist-info/METADATA
filedups-1.0.0.dist-info/WHEEL
filedups-1.0.0.dist-info/top_level.txt
filedups-1.0.0.dist-info/RECORD
