Metadata-Version: 2.1
Name: filedups
Version: 1.0.0
Summary: Local file duplicate finder.
Author-email: Armağan Salmanr <armagansalman+pip@gmail.com>
Project-URL: Homepage, https://github.com/armagansalman/filedups
Classifier: Programming Language :: Python :: 3
Classifier: License :: OSI Approved :: MIT License
Classifier: Operating System :: OS Independent
Requires-Python: >=3.8
License-File: LICENSE.txt
